Tests/__init__.py
Tests/background_workers/__init__.py
Tests/background_workers/controller/__init__.py
Tests/background_workers/controller/test_main_controller.py
Tests/background_workers/controller/test_thread_pool_manager.py
Tests/e2e_tests/__init__.py
Tests/e2e_tests/async_controler_tests/__init__.py
Tests/e2e_tests/async_controler_tests/async_e2e_test.py
Tests/e2e_tests/celery/__init__.py
Tests/e2e_tests/celery/test_celery_and_azure_table_e2e.py
Tests/e2e_tests/celery/test_celery_and_sqlite_e2e.py
Tests/e2e_tests/main/__init__.py
Tests/e2e_tests/main/test_complete_task2.py
Tests/saga/__init__.py
Tests/saga/test_task_creation_saga_azurite.py
Tests/saga/test_task_creation_saga_local_storage.py
Tests/saga/test_task_creation_saga_mock.py
Tests/sample_tasks/__init__.py
Tests/sample_tasks/async_http_fetcher.py
Tests/sample_tasks/multiply_x_by_2.py
Tests/sample_tasks/sample_task.py
Tests/storage/__init__.py
Tests/storage/blob/__init__.py
Tests/storage/blob/test_azure_blob_store.py
Tests/storage/blob/test_local_blob_store.py
Tests/storage/queue/__init__.py
Tests/storage/queue/test_azure_queue_backend.py
Tests/storage/queue/test_local_queue_backend.py
Tests/storage/schemas/__init__.py
Tests/storage/schemas/test_task_entity.py
Tests/storage/schemas/test_task_message.py
Tests/storage/table/__init__.py
Tests/storage/table/test_azure_task_store.py
Tests/storage/table/test_sqlite_task_store.py
Tests/storage/table/tests_test_store_factory.py
Tests/tasks/__init__.py
Tests/tasks/test_base_task.py
Tests/tasks/test_process_single_queue.py
Tests/tests_suites_helpers/__init__.py
Tests/tests_suites_helpers/test_helper.py
Tests/utils/__init__.py
Tests/utils/test_activity_registry.py
Tests/utils/test_decorators.py
Tests/utils/test_dynamic_task_creator.py
Tests/utils/test_workflow_client.py
background_workflows/__init__.py
background_workflows/constants/__init__.py
background_workflows/constants/app_constants.py
background_workflows/controller/__init__.py
background_workflows-0.3.0.dist-info/LICENSE
background_workflows-0.3.0.dist-info/METADATA
background_workflows-0.3.0.dist-info/WHEEL
background_workflows-0.3.0.dist-info/top_level.txt
background_workflows-0.3.0.dist-info/RECORD
