Metadata-Version: 2.1
Name: background-workflows
Version: 0.3.0
Summary: Background Workflows for task processing
Home-page: https://github.com/j-enriquez/background_workflows
Author: Jose Enriquez
Author-email: joseaenriqueza@hotmail.com
License: UNKNOWN
Platform: UNKNOWN
Classifier: Programming Language :: Python :: 3
Classifier: License :: OSI Approved :: MIT License
Classifier: Operating System :: OS Independent
Requires-Python: >=3.6
License-File: LICENSE
Requires-Dist: azure-core (==1.32.0)
Requires-Dist: azure-data-tables (==12.6.0)
Requires-Dist: azure-storage-blob (==12.24.1)
Requires-Dist: azure-storage-queue (==12.12.0)
Requires-Dist: psutil (==5.9.4)
Requires-Dist: python-dotenv (==1.0.1)
Requires-Dist: celery[redis] (==5.2.7)
Requires-Dist: celery[test]
Requires-Dist: aiohttp (==3.11.12)
